{
  "themes/light": {
    "theme": {
      "background": {
        "value": "{colors.gray.100}",
        "description": "Alias value",
        "type": "color"
      },
      "backgroundSubtle": {
        "value": "rgba({colors.gray.100}, 0.5)",
        "description": "Nested color value",
        "type": "color"
      },
      "size": {
        "default": {
          "value": "{sizing.large}",
          "description": "Sizing value",
          "type": "sizing"
        }
      }
    }
  },
  "themes/dark": {
    "theme": {
      "background": {
        "value": "{colors.gray.900}",
        "description": "Alias value",
        "type": "color"
      },
      "backgroundSubtle": {
        "value": "rgba({colors.gray.900}, 0.5)",
        "description": "Nested color value",
        "type": "color"
      },
      "backgroundDark": {
        "value": "{colors.gray.500}",
        "description": "Darkened color value",
        "type": "color",
        "$extensions": {
          "modify": {
            "type": "darken",
            "amount": 0.5,
            "space": "hsl"
          }
        }
      },
      "size": {
        "default": {
          "value": "{sizing.base}",
          "description": "Sizing value",
          "type": "sizing"
        }
      },
      "components": {
        "cards": {
          "default": {
            "type": "composition",
            "value": {
              "borderRadius": "{sizing.base}",
              "fill": "{theme.backgroundSubtle}",
              "border": "{theme.background}"
            }
          }
        }
      }
    }
  },
  "core/shadows": {
    "shadows": {
      "multiple": {
        "value": [
          {
            "color": "{colors.gray.900}",
            "type": "dropShadow",
            "x": "0",
            "y": "4",
            "blur": "2",
            "spread": "0"
          },
          {
            "color": "{colors.gray.900}",
            "type": "dropShadow",
            "x": "0",
            "y": "0",
            "blur": "6",
            "spread": "0"
          }
        ],
        "type": "boxShadow"
      },
      "single": {
        "value": {
          "color": "{colors.gray.900}",
          "type": "dropShadow",
          "x": "0",
          "y": "4",
          "blur": "2",
          "spread": "0"
        },
        "type": "boxShadow"
      },
      "reference-multiple": {
        "value": "{shadows.multiple}",
        "type": "boxShadow"
      },
      "reference-single": {
        "value": "{shadows.single}",
        "type": "boxShadow"
      }
    }
  },
  "core/typography": {
    "typography": {
      "fontFamily": {
        "value": "Roboto",
        "description": "Font value",
        "type": "fontFamilies"
      },
      "fontWeight": {
        "value": "Bold",
        "description": "Weight value",
        "type": "fontWeights"
      },
      "h1": {
        "value": {
          "fontFamily": "{typography.fontFamily}",
          "fontSize": "96",
          "fontWeight": "{typography.fontWeight}"
        },
        "type": "typography"
      },
      "h2": {
        "value": {
          "fontFamily": "{typography.fontFamily}",
          "fontSize": "60",
          "fontWeight": "{typography.fontWeight}"
        },
        "type": "typography"
      },
      "reference": {
        "value": "{typography.h1}",
        "type": "typography"
      }
    }
  },
  "core/border": {
    "border": {
      "base": {
        "value": {
          "width": "{sizing.base}",
          "color": "{colors.gray.900}",
          "style": "solid"
        },
        "description": "Font value",
        "type": "border"
      }
    }
  },
  "core/composition": {
    "composition": {
      "size": {
        "value": "24",
        "type": "sizing"
      },
      "opacity": {
        "value": "50%",
        "type": "opacity"
      },
      "fontFamily": {
        "value": "Roboto",
        "description": "Font value",
        "type": "fontFamilies"
      },
      "fontWeight": {
        "value": "Bold",
        "description": "Weight value",
        "type": "fontWeights"
      },
      "header": {
        "value": {
          "fontFamily": "{composition.fontFamily}",
          "fontSize": "96",
          "fontWeight": "{composition.fontWeight}"
        },
        "type": "composition"
      },
      "body": {
        "value": {
          "width": "{composition.size}",
          "opacity": "{composition.opacity}"
        },
        "type": "composition"
      }
    }
  },
  "base/sizing": {
    "sizing": {
      "base": {
        "value": "4",
        "description": "Alias value",
        "type": "sizing"
      },
      "large": {
        "value": "$sizing.base * 2",
        "description": "Math value",
        "type": "sizing"
      }
    }
  },
  "base/options": {
    "colors": {
      "gray": {
        "100": {
          "value": "#FAFBFC",
          "type": "color"
        },
        "200": {
          "value": "#EAEEF2",
          "type": "color"
        },
        "300": {
          "value": "#D4DAE0",
          "type": "color"
        },
        "400": {
          "value": "#B7BFC7",
          "type": "color"
        },
        "500": {
          "value": "#949DA7",
          "type": "color"
        },
        "600": {
          "value": "#707A84",
          "type": "color"
        },
        "700": {
          "value": "#57606A",
          "type": "color"
        },
        "800": {
          "value": "#424A53",
          "type": "color"
        },
        "900": {
          "value": "#1B1F24",
          "type": "color"
        }
      }
    }
  },
  "$themes": [
    {
      "id": "8f240f308c8cc4acb7106c1073dc37a682997059",
      "name": "themes-light",
      "selectedTokenSets": {
        "base/options": "source",
        "base/sizing": "source",
        "themes/light": "enabled",
        "core/shadows": "enabled"
      },
      "$figmaStyleReferences": {}
    },
    {
      "id": "8f240f308c8cc4acb7106c1073dc37a682997059",
      "name": "themes-dark",
      "selectedTokenSets": {
        "base/options": "source",
        "base/sizing": "source",
        "themes/dark": "enabled",
        "core/shadows": "enabled"
      },
      "$figmaStyleReferences": {}
    }
  ]
}